sphinx_svgio/__init__.py
sphinx_svgio/list/directives.py
sphinx_svgio/list/nodes.py
sphinx_svgio/list/setup.py
sphinx_svgio/refs/node.py
sphinx_svgio/refs/role.py
sphinx_svgio/refs/setup.py
sphinx_svgio/static/__init__.py
sphinx_svgio/static/viewer-static.min.js
sphinx_svgio/svgio/directive.py
sphinx_svgio/svgio/node.py
sphinx_svgio/svgio/setup.py
sphinx_svgio-0.0.9.dist-info/METADATA
sphinx_svgio-0.0.9.dist-info/WHEEL
sphinx_svgio-0.0.9.dist-info/licenses/LICENCE
sphinx_svgio-0.0.9.dist-info/RECORD
