Metadata-Version: 2.4
Name: sphinx_svgio
Version: 0.0.9
Summary: Sphinx extension for drawio embedding
Project-URL: Homepage, https://github.com/Bigyin1/sphinx_svgio
Author: Sergey Aparin
License-Expression: MIT
License-File: LICENCE
Classifier: Operating System :: OS Independent
Classifier: Programming Language :: Python :: 3
Requires-Python: >=3.8
Requires-Dist: importlib-resources
Requires-Dist: sphinx<9,>=7.1
